mqas/__init__.py
mqas/job.py
mqas/misc.py
mqas/queue.py
mqas/script.py
mqas/utils.py
mqas/worker.py
mongo_qas-0.2.5.dist-info/METADATA
mongo_qas-0.2.5.dist-info/WHEEL
mongo_qas-0.2.5.dist-info/entry_points.txt
mongo_qas-0.2.5.dist-info/top_level.txt
mongo_qas-0.2.5.dist-info/RECORD
