Metadata-Version: 2.1
Name: mongo-qas
Version: 0.2.5
Summary: A job queuing and scheduling library based on mongodb
Home-page: https://github.com/giesekow/mongo-qas
Author: Giles Tetteh
Author-email: giles.tetteh@tum.de
Keywords: mongo,queue,schedule,rq
Classifier: Programming Language :: Python :: 3
Classifier: License :: OSI Approved :: MIT License
Classifier: Operating System :: OS Independent
Requires-Dist: pymongo
Requires-Dist: psutil
Requires-Dist: inquirer
Requires-Dist: PyYAML
